{"cameraMode":{"drawMode":0,"name":"Shaded","section":"Shading Mode"},"sceneLighting":true,"audioPlay":false,"sceneViewState":{"showFog":true,"showMaterialUpdate":false,"showSkybox":true,"showFlares":true,"showImageEffects":true,"showParticleSystems":true},"in2DMode":false,"pivot":{"x":-30.007570266723634,"y":-2.1250076293945314,"z":-22.01523208618164},"rotation":{"x":0.011088076047599316,"y":-0.9845044612884522,"z":0.06663836538791657,"w":0.16267575323581696},"size":1.8086556196212769,"orthographic":false}